at_common_tasks/__init__.py
at_common_tasks/tasks/__init__.py
at_common_tasks/tasks/example.py
at_common_tasks/tasks/data/stock.py
at_common_tasks/utils/mappers.py
at_common_tasks/utils/storage.py
at_common_tasks-1.0.9.dist-info/LICENSE
at_common_tasks-1.0.9.dist-info/METADATA
at_common_tasks-1.0.9.dist-info/WHEEL
at_common_tasks-1.0.9.dist-info/top_level.txt
at_common_tasks-1.0.9.dist-info/RECORD
