Metadata-Version: 2.1
Name: at_common_tasks
Version: 1.0.9
Summary: A Python package providing common asynchronous task definitions and utilities for workflow operations.
Author-email: Rui Chen <apextrader.ai@gmail.com>
Project-URL: Homepage, https://github.com/apex-trader/at-common-tasks
Project-URL: Bug Tracker, https://github.com/apex-trader/at-common-tasks/issues
Classifier: Programming Language :: Python :: 3
Classifier: License :: OSI Approved :: MIT License
Classifier: Operating System :: OS Independent
Requires-Python: >=3.11
License-File: LICENSE
Requires-Dist: at_common_workflow>=1.1.15
Requires-Dist: SQLAlchemy>=2.0.36
Requires-Dist: at-common-models>=0.1.3
Requires-Dist: aiomysql>=0.2.0
Requires-Dist: greenlet>=3.0.3
Provides-Extra: dev
Requires-Dist: pytest>=8.3.4; extra == "dev"
Requires-Dist: pytest-asyncio>=0.24.0; extra == "dev"
